.coveragerc
.gitignore
.travis.yml
CHANGES.rst
LICENSE.txt
MANIFEST.in
Makefile
README.rst
requirements-dev.txt
requirements-test.txt
requirements.txt
setup.cfg
setup.py
tox.ini
charlatan/__init__.py
charlatan/_compat.py
charlatan/builder.py
charlatan/depgraph.py
charlatan/file_format.py
charlatan/fixture.py
charlatan/fixture_collection.py
charlatan/fixtures_manager.py
charlatan/testcase.py
charlatan/testing.py
charlatan/utils.py
charlatan.egg-info/PKG-INFO
charlatan.egg-info/SOURCES.txt
charlatan.egg-info/dependency_links.txt
charlatan.egg-info/not-zip-safe
charlatan.egg-info/requires.txt
charlatan.egg-info/top_level.txt
charlatan/tests/__init__.py
charlatan/tests/test_depgraph.py
charlatan/tests/test_file_format.py
charlatan/tests/test_fixture_collection.py
charlatan/tests/test_fixtures_manager.py
charlatan/tests/test_lists_of_fixtures.py
charlatan/tests/test_relationships_without_models.py
charlatan/tests/test_richgetter.py
charlatan/tests/test_simple_testcase.py
charlatan/tests/test_sqlalchemy.py
charlatan/tests/test_testcase.py
charlatan/tests/test_utils.py
charlatan/tests/data/cyclic_dependencies.yaml
charlatan/tests/data/dependencies.yaml
charlatan/tests/data/empty.yaml
charlatan/tests/data/lists.yaml
charlatan/tests/data/relationships.yaml
charlatan/tests/data/relationships_without_models.yaml
charlatan/tests/data/simple.yaml
charlatan/tests/data/special_tags.yaml
charlatan/tests/data/strings.yaml
charlatan/tests/data/test.json
charlatan/tests/example/__init__.py
charlatan/tests/example/test_custom_builder.py
charlatan/tests/example/test_deep_inherit.py
charlatan/tests/example/test_sqlalchemy.py
charlatan/tests/example/data/custom_builder.yaml
charlatan/tests/example/data/deep_inherit.yaml
charlatan/tests/example/data/sqlalchemy.yaml
charlatan/tests/fixtures/__init__.py
charlatan/tests/fixtures/models.py
charlatan/tests/fixtures/simple_models.py
docs/Makefile
docs/api-reference.rst
docs/builders.rst
docs/changelog.rst
docs/conf.py
docs/contributing.rst
docs/database.rst
docs/file-format.rst
docs/hooks.rst
docs/index.rst
docs/installation.rst
docs/make.bat
docs/quickstart.rst
docs/examples/collection.yaml
docs/examples/dependencies.yaml
