Metadata-Version: 1.1
Name: charlatan
Version: 0.4.6
Summary: Efficiently manage and install data fixtures
Home-page: https://github.com/uber/charlatan
Author: Charles-Axel Dein
Author-email: charles@uber.com
License: MIT
Keywords: tests,fixtures,database
Platform: UNKNOWN
Classifier: Development Status :: 4 - Beta
Classifier: Programming Language :: Python
Classifier: Programming Language :: Python :: 2.7
Classifier: Programming Language :: Python :: 3
Classifier: Programming Language :: Python :: 3.3
Classifier: Intended Audience :: Developers
Classifier: License :: OSI Approved :: MIT License
Classifier: Operating System :: OS Independent
Classifier: Topic :: Software Development :: Testing
Classifier: Topic :: Software Development :: Libraries :: Python Modules
